web2sdk/__init__.py
web2sdk/console_util.py
web2sdk/main.py
web2sdk/swagger2sdk/__init__.py
web2sdk/swagger2sdk/generate_function.py
web2sdk/swagger2sdk/generate_types.py
web2sdk/swagger2sdk/main.py
web2sdk/swagger2sdk/utils.py
web2sdk/tests/__init__.py
web2sdk/web2swagger/.DS_Store
web2sdk/web2swagger/__init__.py
web2sdk/web2swagger/har_capture_reader.py
web2sdk/web2swagger/main.py
web2sdk/web2swagger/mitmproxy_capture_reader.py
web2sdk/web2swagger/swagger_util.py
web2sdk-0.0.3.dist-info/LICENSE
web2sdk-0.0.3.dist-info/METADATA
web2sdk-0.0.3.dist-info/WHEEL
web2sdk-0.0.3.dist-info/entry_points.txt
web2sdk-0.0.3.dist-info/RECORD
