Metadata-Version: 2.1
Name: web2sdk
Version: 0.0.3
Summary: Reverse engineer third party APIs into python SDKs
Author: jasonwcfan
Author-email: jason.wc.fan@gmail.com
Requires-Python: >=3.10,<4.0
Classifier: Programming Language :: Python :: 3
Classifier: Programming Language :: Python :: 3.10
Classifier: Programming Language :: Python :: 3.11
Requires-Dist: astor (>=0.8.1,<0.9.0)
Requires-Dist: json-stream (>=2.3.2,<3.0.0)
Requires-Dist: mitmproxy (>=10.1.1,<11.0.0)
Requires-Dist: msgpack (>=1.0.7,<2.0.0)
Requires-Dist: pydantic (>=2.8.2,<3.0.0)
Requires-Dist: python-dotenv (>=1.0.1,<2.0.0)
Requires-Dist: pyyaml (>=6.0.2,<7.0.0)
Requires-Dist: requests (>=2.32.3,<3.0.0)
Requires-Dist: ruamel.yaml (>=0.17.32,<0.19.0)
